gitmate/__init__.py
gitmate/cli.py
gitmate_ai-2.0.0.dist-info/licenses/LICENSE
gitmate_ai-2.0.0.dist-info/METADATA
gitmate_ai-2.0.0.dist-info/WHEEL
gitmate_ai-2.0.0.dist-info/entry_points.txt
gitmate_ai-2.0.0.dist-info/top_level.txt
gitmate_ai-2.0.0.dist-info/RECORD
