Metadata-Version: 2.4
Name: gitmate-ai
Version: 2.0.0
Summary: GitMate - AI Git Assistant for Terminal
Author: Tejas Raundal
Requires-Python: >=3.8
License-File: LICENSE
Requires-Dist: rich
Requires-Dist: langchain
Requires-Dist: langchain-google-genai
Requires-Dist: langchain-openai
Requires-Dist: langchain-anthropic
Dynamic: author
Dynamic: description
Dynamic: description-content-type
Dynamic: license-file
Dynamic: requires-dist
Dynamic: requires-python
Dynamic: summary
